ucup/__init__.py
ucup/advanced_probabilistic.py
ucup/agent_monitoring.py
ucup/api_discovery.py
ucup/build_wrapper.py
ucup/causal_analysis.py
ucup/cli.py
ucup/cloud_deployment.py
ucup/config.py
ucup/coordination.py
ucup/deployment.py
ucup/deployment_automation.py
ucup/email_reporting.py
ucup/errors.py
ucup/feature_flags.py
ucup/gemini_adapter.py
ucup/memory_management.py
ucup/metrics.py
ucup/multimodal.py
ucup/observability.py
ucup/plugins.py
ucup/predictive_failure.py
ucup/probabilistic.py
ucup/probabilistic_debugger.py
ucup/pytest_plugin.py
ucup/reliability.py
ucup/self_healing.py
ucup/smart_recommendations.py
ucup/smart_suggestions.py
ucup/test_environments.py
ucup/testing.py
ucup/time_travel_debugger.py
ucup/uncertainty_visualizer.py
ucup/validation.py
ucup/visualization.py
ucup/multimodal/__init__.py
ucup/multimodal/fusion_engine.py
ucup/multimodal/streaming_processor.py
ucup/performance/__init__.py
ucup/performance/async_processing.py
ucup/performance/bayesian_optimizer.py
ucup/performance/distributed.py
ucup/performance/memory_manager.py
ucup/plugins/__init__.py
ucup/plugins/base.py
ucup/plugins/donation_plugin.py
ucup/plugins/example_agent.py
ucup/plugins/example_strategy.py
ucup/plugins/monitoring_plugin.py
ucup/testing/multimodal_agent_tester.py
ucup/testing/intelligent/__init__.py
ucup/testing/intelligent/generator.py
ucup/toon/__init__.py
ucup/toon/toon_formatter.py
ucup/toon/validation.py
ucup-4.0.1.dist-info/licenses/LICENSE
ucup-4.0.1.dist-info/METADATA
ucup-4.0.1.dist-info/WHEEL
ucup-4.0.1.dist-info/entry_points.txt
ucup-4.0.1.dist-info/top_level.txt
ucup-4.0.1.dist-info/RECORD
